path_explorator/__init__.py
path_explorator/core/__init__.py
path_explorator/core/validator.py
path_explorator/core/explorer/__init__.py
path_explorator/core/explorer/directory/__init__.py
path_explorator/core/explorer/directory/actor.py
path_explorator/core/explorer/directory/directory_explorer.py
path_explorator/core/explorer/path/__init__.py
path_explorator/core/explorer/path/path_cleaner.py
path_explorator/core/explorer/path/path_creator.py
path_explorator/core/explorer/path/path_reader.py
path_explorator/exceptions/__init__.py
path_explorator/exceptions/entity_exc.py
path_explorator/exceptions/path_exc.py
path_explorator/utils/__init__.py
path_explorator/utils/path_cutter.py
path_explorator-0.0.7.dist-info/licenses/LICENSE
path_explorator-0.0.7.dist-info/METADATA
path_explorator-0.0.7.dist-info/WHEEL
path_explorator-0.0.7.dist-info/top_level.txt
path_explorator-0.0.7.dist-info/RECORD
