Metadata-Version: 2.4
Name: path_explorator
Version: 0.0.7
Summary: Wrapper for a pathlib
Author-email: BUTCHHO <skeletorkoltmm@gmail.com>
License: MIT
Project-URL: Homepage, https://github.com/BUTCHHO/path-explorator
Requires-Python: >=3.10
License-File: LICENSE
Dynamic: license-file
